ab_openapi_python_generator/__init__.py
ab_openapi_python_generator/__main__.py
ab_openapi_python_generator/common.py
ab_openapi_python_generator/generate_data.py
ab_openapi_python_generator/models.py
ab_openapi_python_generator/py.typed
ab_openapi_python_generator/version_detector.py
ab_openapi_python_generator/language_converters/__init__.py
ab_openapi_python_generator/language_converters/python/__init__.py
ab_openapi_python_generator/language_converters/python/client_generator.py
ab_openapi_python_generator/language_converters/python/common.py
ab_openapi_python_generator/language_converters/python/exception_generator.py
ab_openapi_python_generator/language_converters/python/generator.py
ab_openapi_python_generator/language_converters/python/jinja_config.py
ab_openapi_python_generator/language_converters/python/model_generator.py
ab_openapi_python_generator/language_converters/python/templates/alias_union.jinja2
ab_openapi_python_generator/language_converters/python/templates/async_client_httpx_pydantic_2.jinja2
ab_openapi_python_generator/language_converters/python/templates/discriminator_enum.jinja2
ab_openapi_python_generator/language_converters/python/templates/enum.jinja2
ab_openapi_python_generator/language_converters/python/templates/http_exception.jinja2
ab_openapi_python_generator/language_converters/python/templates/models.jinja2
ab_openapi_python_generator/language_converters/python/templates/models_pydantic_2.jinja2
ab_openapi_python_generator/language_converters/python/templates/sync_client_httpx_pydantic_2.jinja2
ab_openapi_python_generator/parsers/__init__.py
ab_openapi_python_generator/parsers/openapi_30.py
ab_openapi_python_generator/parsers/openapi_31.py
ab_openapi_python_generator-2.2.3.dist-info/METADATA
ab_openapi_python_generator-2.2.3.dist-info/WHEEL
ab_openapi_python_generator-2.2.3.dist-info/entry_points.txt
ab_openapi_python_generator-2.2.3.dist-info/licenses/LICENSE
ab_openapi_python_generator-2.2.3.dist-info/RECORD
