Metadata-Version: 2.4
Name: ab-openapi-python-generator
Version: 2.2.3
Summary: Openapi Python Generator
Project-URL: Homepage, https://github.com/auth-broker/openapi-python-generator
Project-URL: Repository, https://github.com/auth-broker/openapi-python-generator
Project-URL: Documentation, https://openapi-python-generator.readthedocs.io
Project-URL: Changelog, https://github.com/auth-broker/openapi-python-generator/releases
Author-email: Marco Müllner <muellnermarco@gmail.com>, Matt Coulter <mattcoul7@gmail.com>
License-Expression: MIT
License-File: LICENSE
Keywords: Generator,OpenAPI,Python,async
Classifier: Development Status :: 3 - Alpha
Requires-Python: <4,>=3.9
Requires-Dist: black>=21.10b0
Requires-Dist: click<9,>=8.1.3
Requires-Dist: httpx[all]<0.29,>=0.28.0
Requires-Dist: importlib-metadata<9,>=8.7.0
Requires-Dist: isort>=5.10.1
Requires-Dist: jinja2<4,>=3.1.2
Requires-Dist: openapi-pydantic<0.6,>=0.5.1
Requires-Dist: orjson<4,>=3.9.15
Requires-Dist: pydantic<3,>=2.10.2
Requires-Dist: pyyaml<7,>=6.0.2
